dffml_feature_git/__init__.py
dffml_feature_git/log.py
dffml_feature_git/version.py
dffml_feature_git/feature/__init__.py
dffml_feature_git/feature/definitions.py
dffml_feature_git/feature/log.py
dffml_feature_git/feature/operations.py
dffml_feature_git/util/__init__.py
dffml_feature_git/util/log.py
dffml_feature_git/util/proc.py
tests/__init__.py
tests/test_df.py
dffml_feature_git-0.3.0.post0.dist-info/LICENSE
dffml_feature_git-0.3.0.post0.dist-info/METADATA
dffml_feature_git-0.3.0.post0.dist-info/WHEEL
dffml_feature_git-0.3.0.post0.dist-info/entry_points.txt
dffml_feature_git-0.3.0.post0.dist-info/top_level.txt
dffml_feature_git-0.3.0.post0.dist-info/RECORD
