Metadata-Version: 2.1
Name: dffml-feature-git
Version: 0.3.0.post0
Summary: UNKNOWN
Home-page: https://github.com/intel/dffml/blob/master/feature/git/README.md
Author: John Andersen
Author-email: john.s.andersen@intel.com
License: MIT
Platform: UNKNOWN
Classifier: Development Status :: 3 - Alpha
Classifier: Intended Audience :: Developers
Classifier: License :: OSI Approved :: MIT License
Classifier: License :: OSI Approved :: Apache Software License
Classifier: Natural Language :: English
Classifier: Operating System :: OS Independent
Classifier: Programming Language :: Python :: 3.7
Classifier: Programming Language :: Python :: Implementation :: CPython
Classifier: Programming Language :: Python :: Implementation :: PyPy
License-File: LICENSE
Requires-Dist: dffml (>=0.4.0)
Requires-Dist: python-dateutil (>=2.7.3)
